.DS_Store
pytorch_pretrained_bert/__init__.py
pytorch_pretrained_bert/__main__.py
pytorch_pretrained_bert/convert_gpt2_checkpoint_to_pytorch.py
pytorch_pretrained_bert/convert_openai_checkpoint_to_pytorch.py
pytorch_pretrained_bert/convert_tf_checkpoint_to_pytorch.py
pytorch_pretrained_bert/convert_transfo_xl_checkpoint_to_pytorch.py
pytorch_pretrained_bert/file_utils.py
pytorch_pretrained_bert/modeling.py
pytorch_pretrained_bert/modeling_gpt2.py
pytorch_pretrained_bert/modeling_openai.py
pytorch_pretrained_bert/modeling_transfo_xl.py
pytorch_pretrained_bert/modeling_transfo_xl_utilities.py
pytorch_pretrained_bert/optimization.py
pytorch_pretrained_bert/optimization_openai.py
pytorch_pretrained_bert/tokenization.py
pytorch_pretrained_bert/tokenization_gpt2.py
pytorch_pretrained_bert/tokenization_openai.py
pytorch_pretrained_bert/tokenization_transfo_xl.py
pytorch_pretrained_bert-0.6.1.dist-info/LICENSE
pytorch_pretrained_bert-0.6.1.dist-info/METADATA
pytorch_pretrained_bert-0.6.1.dist-info/WHEEL
pytorch_pretrained_bert-0.6.1.dist-info/entry_points.txt
pytorch_pretrained_bert-0.6.1.dist-info/top_level.txt
pytorch_pretrained_bert-0.6.1.dist-info/RECORD
