Metadata-Version: 2.1
Name: pytorch-pretrained-bert
Version: 0.6.1
Summary: PyTorch version of Google AI BERT model with script to load Google pre-trained models
Home-page: https://github.com/huggingface/pytorch-pretrained-BERT
Author: Thomas Wolf, Victor Sanh, Tim Rault, Google AI Language Team Authors, Open AI team Authors
Author-email: thomas@huggingface.co
License: Apache
Keywords: BERT NLP deep learning google
Platform: UNKNOWN
Classifier: Intended Audience :: Science/Research
Classifier: License :: OSI Approved :: Apache Software License
Classifier: Programming Language :: Python :: 3
Classifier: Topic :: Scientific/Engineering :: Artificial Intelligence
Requires-Dist: torch (>=0.4.1)
Requires-Dist: numpy
Requires-Dist: boto3
Requires-Dist: requests
Requires-Dist: tqdm
Requires-Dist: regex
